{
  "tournamentSlug": "sugrobushki-2026",
  "title": "ИСИ (Индивидуальная Своя Игра)",
  "seedSource": "отбор",
  "qualification": [
    {
      "place": 1,
      "name": "Наталья Комар",
      "total": 800
    },
    {
      "place": 2,
      "name": "Антон Короткевич",
      "total": 670
    },
    {
      "place": 3,
      "name": "Дмитрий Овчарук",
      "total": 660
    },
    {
      "place": 4,
      "name": "Виктор Реут",
      "total": 600
    },
    {
      "place": 5,
      "name": "Артемий Беляев",
      "total": 580
    },
    {
      "place": 6,
      "name": "Дмитрий Литвинов",
      "total": 540
    },
    {
      "place": 7,
      "name": "Дмитрий Попов",
      "total": 530
    },
    {
      "place": 8,
      "name": "Николай Лёгенький",
      "total": 520
    },
    {
      "place": 9,
      "name": "Антон Моисеев",
      "total": 520
    },
    {
      "place": 10,
      "name": "Ирина Чернуха + Иделия Айзятулова (вне зачёта)",
      "total": 520,
      "note": "вне зачёта"
    },
    {
      "place": 10,
      "name": "Олег Волков",
      "total": 500
    },
    {
      "place": 11,
      "name": "Алексей Винокуров",
      "total": 500
    },
    {
      "place": 12,
      "name": "Михаил Циплев",
      "total": 490
    },
    {
      "place": 13,
      "name": "Саша Ваксман",
      "total": 490
    },
    {
      "place": 14,
      "name": "Леша Пак",
      "total": 480
    },
    {
      "place": 15,
      "name": "Ольга Александрова",
      "total": 470
    },
    {
      "place": 16,
      "name": "Леонид Михлин",
      "total": 460
    },
    {
      "place": 17,
      "name": "Дмитрий Панкратов",
      "total": 460
    },
    {
      "place": 18,
      "name": "Амаль Имангулов",
      "total": 460
    },
    {
      "place": 19,
      "name": "Глеб Николаев",
      "total": 450
    },
    {
      "place": 20,
      "name": "Александр Котляров",
      "total": 450
    },
    {
      "place": 21,
      "name": "Кирилл Берёзкин",
      "total": 440
    },
    {
      "place": 22,
      "name": "Владимир Осипчук",
      "total": 430
    },
    {
      "place": 23,
      "name": "Станислав Адаскевич",
      "total": 390
    },
    {
      "place": 24,
      "name": "Андрей Маврин",
      "total": 380
    },
    {
      "place": 25,
      "name": "Дмитрий Сумин",
      "total": 380
    },
    {
      "place": 26,
      "name": "Олег Павлов",
      "total": 360
    },
    {
      "place": 27,
      "name": "Максим Крайнов",
      "total": 350
    },
    {
      "place": 28,
      "name": "Екатерина Щуплова",
      "total": 350
    },
    {
      "place": 29,
      "name": "Андрей Рыхальский",
      "total": 340
    },
    {
      "place": 30,
      "name": "Анастасия Чехова",
      "total": 340
    },
    {
      "place": 31,
      "name": "Булат Фаттахов",
      "total": 330
    },
    {
      "place": 32,
      "name": "Евгений Гацак",
      "total": 320
    },
    {
      "place": 33,
      "name": "Глеб Попов",
      "total": 320
    },
    {
      "place": 34,
      "name": "Сергей Морозов",
      "total": 320
    },
    {
      "place": 35,
      "name": "Ксения Шагал",
      "total": 310
    },
    {
      "place": 36,
      "name": "Георгий Гветадзе",
      "total": 300
    },
    {
      "place": 37,
      "name": "Влад Дейкун",
      "total": 300
    },
    {
      "place": 38,
      "name": "Дмитрий Арбузов",
      "total": 300
    },
    {
      "place": 39,
      "name": "Евгений Момотов",
      "total": 300
    },
    {
      "place": 40,
      "name": "Кирилл Рукавицын",
      "total": 280
    },
    {
      "place": 41,
      "name": "Алексей Дударев",
      "total": 280
    },
    {
      "place": 42,
      "name": "Егор Сидорович",
      "total": 280
    },
    {
      "place": 43,
      "name": "Павел Чиж",
      "total": 280
    },
    {
      "place": 44,
      "name": "Павел Свярдлоў",
      "total": 270
    },
    {
      "place": 45,
      "name": "Александр Потапенко",
      "total": 260
    },
    {
      "place": 46,
      "name": "Александр Петровский",
      "total": 260
    },
    {
      "place": 47,
      "name": "Денис Алимов",
      "total": 260
    },
    {
      "place": 48,
      "name": "Антон Стародинов",
      "total": 250
    },
    {
      "place": 49,
      "name": "Владислав Дронов",
      "total": 250
    },
    {
      "place": 50,
      "name": "Мария Иванова",
      "total": 250
    },
    {
      "place": 51,
      "name": "Арсений Мустафин",
      "total": 250
    },
    {
      "place": 52,
      "name": "Владимир Тулин",
      "total": 240
    },
    {
      "place": 53,
      "name": "Галина Пактовская",
      "total": 240
    },
    {
      "place": 54,
      "name": "Антон Филиппов",
      "total": 240
    },
    {
      "place": 55,
      "name": "Артур Хамитов",
      "total": 240
    },
    {
      "place": 56,
      "name": "Андрей Лутенко",
      "total": 240
    },
    {
      "place": 57,
      "name": "Максим Шапоров",
      "total": 230
    },
    {
      "place": 58,
      "name": "Pronkevich Konstantin",
      "total": 230
    },
    {
      "place": 59,
      "name": "Тимчук Андрей",
      "total": 230
    },
    {
      "place": 60,
      "name": "Егор Куликов",
      "total": 220
    },
    {
      "place": 61,
      "name": "Евгений Островерх",
      "total": 220
    },
    {
      "place": 62,
      "name": "Мария Топаж",
      "total": 220
    },
    {
      "place": 63,
      "name": "Оксана Бандура",
      "total": 220
    },
    {
      "place": 64,
      "name": "Михаил Трифонов",
      "total": 210
    },
    {
      "place": 65,
      "name": "Владислава Плохих",
      "total": 210
    },
    {
      "place": 66,
      "name": "Владимир Васильев",
      "total": 200
    },
    {
      "place": 67,
      "name": "Юрий Рудык",
      "total": 200
    },
    {
      "place": 68,
      "name": "Ксения Накладова",
      "total": 190
    },
    {
      "place": 69,
      "name": "Анна Никонова",
      "total": 190
    },
    {
      "place": 70,
      "name": "Денис Ершов",
      "total": 170
    },
    {
      "place": 71,
      "name": "Максим Воронецкий",
      "total": 170
    },
    {
      "place": 72,
      "name": "Александр Бивейнис",
      "total": 160
    },
    {
      "place": 73,
      "name": "Эдуард Вербицкий",
      "total": 160
    },
    {
      "place": 74,
      "name": "Михаил Ерасов",
      "total": 160
    },
    {
      "place": 75,
      "name": "Эдвин Станкевич",
      "total": 160
    },
    {
      "place": 76,
      "name": "Константин Лаврисюк",
      "total": 160
    },
    {
      "place": 77,
      "name": "Марина Янковская",
      "total": 150
    },
    {
      "place": 78,
      "name": "Анатолий Бородин",
      "total": 150
    },
    {
      "place": 79,
      "name": "Артур Хацук",
      "total": 150
    },
    {
      "place": 80,
      "name": "Владимир Замятин",
      "total": 140
    },
    {
      "place": 81,
      "name": "Алексей Рахманов",
      "total": 140
    },
    {
      "place": 82,
      "name": "Михаил Кольцов",
      "total": 140
    },
    {
      "place": 83,
      "name": "Иван Миленин",
      "total": 140
    },
    {
      "place": 84,
      "name": "Светлана Стреж",
      "total": 140
    },
    {
      "place": 85,
      "name": "Кенкадзе Шанше",
      "total": 140
    },
    {
      "place": 86,
      "name": "Дмитрий Бибичков",
      "total": 120
    },
    {
      "place": 87,
      "name": "Дмитрий Сергейчик",
      "total": 120
    },
    {
      "place": 88,
      "name": "Илья Томилович",
      "total": 120
    },
    {
      "place": 89,
      "name": "Андрій Назарчук",
      "total": 110
    },
    {
      "place": 90,
      "name": "Сергей Гребенюк",
      "total": 110
    },
    {
      "place": 91,
      "name": "Артем Ненашев",
      "total": 100
    },
    {
      "place": 92,
      "name": "Наталевич Михаил",
      "total": 100
    },
    {
      "place": 93,
      "name": "Serghei Gherghelejiu",
      "total": 90
    },
    {
      "place": 94,
      "name": "Елизавета Гангрская",
      "total": 90
    },
    {
      "place": 95,
      "name": "Ольга Максимова",
      "total": 70
    },
    {
      "place": 96,
      "name": "Наталья Ненашева",
      "total": 70
    },
    {
      "place": 97,
      "name": "Нелли Зайдман",
      "total": 40
    },
    {
      "place": 98,
      "name": "Аляксандр Русак",
      "total": 40
    },
    {
      "place": 99,
      "name": "Инна Шаля",
      "total": -110
    }
  ],
  "playoffs": {
    "bouts": [
      {
        "label": "Группа А, главный зал 1",
        "matches": [
          {
            "player": "Антон Моисеев",
            "score": 90,
            "scoreRaw": "90",
            "place": 2
          },
          {
            "player": "Леонид Михлин",
            "score": 0,
            "scoreRaw": "0",
            "place": 4
          },
          {
            "player": "Дмитрий Панкратов",
            "score": 210,
            "scoreRaw": "210",
            "place": 1
          },
          {
            "player": "Андрей Маврин",
            "score": 30,
            "scoreRaw": "30",
            "place": 3
          },
          {
            "player": "Олег Волков",
            "score": 200,
            "scoreRaw": "200",
            "place": 1
          },
          {
            "player": "Ольга Александрова",
            "score": 120,
            "scoreRaw": "120",
            "place": 3
          },
          {
            "player": "Амаль Имангулов",
            "score": 10,
            "scoreRaw": "10",
            "place": 4
          },
          {
            "player": "Станислав Адаскевич",
            "score": 130,
            "scoreRaw": "130",
            "place": 2
          },
          {
            "player": "Алексей Винокуров",
            "score": 80,
            "scoreRaw": "80",
            "place": 3
          },
          {
            "player": "Леша Пак",
            "score": 160,
            "scoreRaw": "160",
            "place": 1
          },
          {
            "player": "Глеб Николаев",
            "score": 160,
            "scoreRaw": "160",
            "place": 1
          },
          {
            "player": "Владимир Осипчук",
            "score": 60,
            "scoreRaw": "60",
            "place": 4
          },
          {
            "player": "Михаил Циплев",
            "score": 30,
            "scoreRaw": "30",
            "place": 4
          },
          {
            "player": "Саша Ваксман",
            "score": 140,
            "scoreRaw": "140",
            "place": 2
          },
          {
            "player": "Александр Котляров",
            "score": 90,
            "scoreRaw": "90",
            "place": 3
          },
          {
            "player": "Кирилл Берёзкин",
            "score": 150,
            "scoreRaw": "150",
            "place": 1
          }
        ]
      },
      {
        "label": "Группа E, главный зал 1",
        "matches": [
          {
            "player": "Наталья Комар",
            "score": 120,
            "scoreRaw": "120",
            "place": 2
          },
          {
            "player": "Николай Лёгенький",
            "score": 140,
            "scoreRaw": "140",
            "place": 1
          },
          {
            "player": "Дмитрий Панкратов",
            "score": 110,
            "scoreRaw": "110",
            "place": 3
          },
          {
            "player": "Антон Моисеев",
            "score": 10,
            "scoreRaw": "10",
            "place": 4
          },
          {
            "player": "Антон Короткевич",
            "score": 110,
            "scoreRaw": "110",
            "place": 1
          },
          {
            "player": "Дмитрий Попов",
            "score": 0,
            "scoreRaw": "0",
            "place": 4
          },
          {
            "player": "Олег Волков",
            "score": 100,
            "scoreRaw": "100",
            "place": 2
          },
          {
            "player": "Станислав Адаскевич",
            "score": 0,
            "scoreRaw": "0",
            "place": 4
          },
          {
            "player": "Дмитрий Овчарук",
            "score": 70,
            "scoreRaw": "70",
            "place": 3
          },
          {
            "player": "Дмитрий Литвинов",
            "score": 10,
            "scoreRaw": "10",
            "place": 4
          },
          {
            "player": "Лёша Пак",
            "score": 100,
            "scoreRaw": "100",
            "place": 2
          },
          {
            "player": "Глеб Николаев",
            "score": 120,
            "scoreRaw": "120",
            "place": 1
          },
          {
            "player": "Виктор Реут",
            "score": 120,
            "scoreRaw": "120",
            "place": 2
          },
          {
            "player": "Артемий Беляев",
            "score": -20,
            "scoreRaw": "-20",
            "place": 4
          },
          {
            "player": "Кирилл Березкин",
            "score": 140,
            "scoreRaw": "140",
            "place": 1
          },
          {
            "player": "Саша Ваксман",
            "score": 10,
            "scoreRaw": "10",
            "place": 3
          }
        ]
      },
      {
        "label": "П1, главный зал 1",
        "matches": [
          {
            "player": "Николай Лёгенький",
            "score": 230,
            "scoreRaw": "230",
            "place": 2
          },
          {
            "player": "Олег Волков",
            "score": 40,
            "scoreRaw": "40",
            "place": 4
          },
          {
            "player": "Лёша Пак",
            "score": 90,
            "scoreRaw": "90",
            "place": 3
          },
          {
            "player": "Кирилл Березкин",
            "score": 250,
            "scoreRaw": "250",
            "place": 1
          },
          {
            "player": "Наталья Комар",
            "score": 320,
            "scoreRaw": "320",
            "place": 1
          },
          {
            "player": "Антон Короткевич",
            "score": 170,
            "scoreRaw": "170",
            "place": 2
          },
          {
            "player": "Глеб Николаев",
            "score": 150,
            "scoreRaw": "150",
            "place": 3
          },
          {
            "player": "Виктор Реут",
            "score": 70,
            "scoreRaw": "70",
            "place": 4
          }
        ]
      },
      {
        "label": "главный зал",
        "matches": [
          {
            "player": "Кирилл Березкин",
            "score": 40,
            "scoreRaw": "40",
            "place": 4
          },
          {
            "player": "Николай Лёгенький",
            "score": 150,
            "scoreRaw": "150",
            "place": 3
          },
          {
            "player": "Наталья Комар",
            "score": 190,
            "scoreRaw": "190",
            "place": 2
          },
          {
            "player": "Антон Короткевич",
            "score": 230,
            "scoreRaw": "230",
            "place": 1
          }
        ]
      }
    ],
    "seeds": [
      {
        "place": 1,
        "name": "Наталья Комар"
      },
      {
        "place": 2,
        "name": "Антон Короткевич"
      },
      {
        "place": 3,
        "name": "Дмитрий Овчарук"
      },
      {
        "place": 4,
        "name": "Виктор Реут"
      },
      {
        "place": 5,
        "name": "Артемий Беляев"
      },
      {
        "place": 6,
        "name": "Дмитрий Литвинов"
      },
      {
        "place": 7,
        "name": "Дмитрий Попов"
      },
      {
        "place": 8,
        "name": "Николай Лёгенький"
      },
      {
        "place": 9,
        "name": "Антон Моисеев"
      },
      {
        "place": 10,
        "name": "Ирина Чернуха + Иделия Айзятулова (вне зачёта)"
      },
      {
        "place": 10,
        "name": "Олег Волков"
      },
      {
        "place": 11,
        "name": "Алексей Винокуров"
      },
      {
        "place": 12,
        "name": "Михаил Циплев"
      },
      {
        "place": 13,
        "name": "Саша Ваксман"
      },
      {
        "place": 14,
        "name": "Леша Пак"
      },
      {
        "place": 15,
        "name": "Ольга Александрова"
      },
      {
        "place": 16,
        "name": "Леонид Михлин"
      },
      {
        "place": 17,
        "name": "Дмитрий Панкратов"
      },
      {
        "place": 18,
        "name": "Амаль Имангулов"
      },
      {
        "place": 19,
        "name": "Глеб Николаев"
      },
      {
        "place": 20,
        "name": "Александр Котляров"
      },
      {
        "place": 21,
        "name": "Кирилл Берёзкин"
      },
      {
        "place": 22,
        "name": "Владимир Осипчук"
      },
      {
        "place": 23,
        "name": "Станислав Адаскевич"
      }
    ]
  }
}
